{"ServiceDelivery":{"ResponseTimestamp":"2025-03-28T19:48:44Z","ProducerRef":"SF","Status":true,"StopMonitoringDelivery":{"version":"1.4","ResponseTimestamp":"2025-03-28T19:48:44Z","Status":true,"MonitoredStopVisit":[{"RecordedAtTime":"2025-03-28T19:48:42Z","MonitoringRef":"17073","MonitoredVehicleJourney":{"LineRef":"J","DirectionRef":"IB","FramedVehicleJourneyRef":{"DataFrameRef":"2025-03-28","DatedVehicleJourneyRef":"11734716_M31"},"PublishedLineName":"CHURCH","OperatorRef":"SF","OriginRef":"17778","OriginName":"San Jose Ave & Geneva Ave","DestinationRef":"16992","DestinationName":"Metro Embarcadero Station","Monitored":true,"InCongestion":null,"VehicleLocation":{"Longitude":"-122.427155","Latitude":"37.7561607"},"Bearing":"30.0000000000","Occupancy":"seatsAvailable","VehicleRef":"2112","MonitoredCall":{"StopPointRef":"17073","StopPointName":"Church St & Market St","VehicleLocationAtStop":"","VehicleAtStop":"false","DestinationDisplay":"Embarcadero Station","AimedArrivalTime":"2025-03-28T19:47:37Z","ExpectedArrivalTime":"2025-03-28T19:56:47Z","AimedDepartureTime":"2025-03-28T19:47:37Z","ExpectedDepartureTime":null,"Distances":""}}},{"RecordedAtTime":"2025-03-28T19:48:42Z","MonitoringRef":"17073","MonitoredVehicleJourney":{"LineRef":"22","DirectionRef":"IB","FramedVehicleJourneyRef":{"DataFrameRef":"2025-03-28","DatedVehicleJourneyRef":"11749158_M31"},"PublishedLineName":"FILLMORE","OperatorRef":"SF","OriginRef":"17765","OriginName":"Mission Bay North & 3rd St","DestinationRef":"14603","DestinationName":"Fillmore St & Bay St","Monitored":true,"InCongestion":null,"VehicleLocation":{"Longitude":"-122.413155","Latitude":"37.7655067"},"Bearing":"255.0000000000","Occupancy":"standingAvailable","VehicleRef":"5717","MonitoredCall":{"StopPointRef":"17073","StopPointName":"Church St & Market St","VehicleLocationAtStop":"","VehicleAtStop":"false","DestinationDisplay":"Bay Street","AimedArrivalTime":"2025-03-28T19:52:00Z","ExpectedArrivalTime":"2025-03-28T19:57:35Z","AimedDepartureTime":"2025-03-28T19:52:00Z","ExpectedDepartureTime":null,"Distances":""}}},{"RecordedAtTime":"2025-03-28T19:48:42Z","MonitoringRef":"17073","MonitoredVehicleJourney":{"LineRef":"22","DirectionRef":"IB","FramedVehicleJourneyRef":{"DataFrameRef":"2025-03-28","DatedVehicleJourneyRef":"11749159_M31"},"PublishedLineName":"FILLMORE","OperatorRef":"SF","OriginRef":"17765","OriginName":"Mission Bay North & 3rd St","DestinationRef":"14603","DestinationName":"Fillmore St & Bay St","Monitored":true,"InCongestion":null,"VehicleLocation":{"Longitude":"-122.410065","Latitude":"37.7657204"},"Bearing":"255.0000000000","Occupancy":"seatsAvailable","VehicleRef":"5713","MonitoredCall":{"StopPointRef":"17073","StopPointName":"Church St & Market St","VehicleLocationAtStop":"","VehicleAtStop":"false","DestinationDisplay":"Bay Street","AimedArrivalTime":"2025-03-28T19:58:00Z","ExpectedArrivalTime":"2025-03-28T19:59:05Z","AimedDepartureTime":"2025-03-28T19:58:00Z","ExpectedDepartureTime":null,"Distances":""}}},{"RecordedAtTime":"2025-03-28T19:48:42Z","MonitoringRef":"17073","MonitoredVehicleJourney":{"LineRef":"22","DirectionRef":"IB","FramedVehicleJourneyRef":{"DataFrameRef":"2025-03-28","DatedVehicleJourneyRef":"11749160_M31"},"PublishedLineName":"FILLMORE","OperatorRef":"SF","OriginRef":"17765","OriginName":"Mission Bay North & 3rd St","DestinationRef":"14603","DestinationName":"Fillmore St & Bay St","Monitored":true,"InCongestion":null,"VehicleLocation":{"Longitude":"-122.397476","Latitude":"37.7664604"},"Bearing":"255.0000000000","Occupancy":"seatsAvailable","VehicleRef":"5734","MonitoredCall":{"StopPointRef":"17073","StopPointName":"Church St & Market St","VehicleLocationAtStop":"","VehicleAtStop":"false","DestinationDisplay":"Bay Street","AimedArrivalTime":"2025-03-28T20:05:00Z","ExpectedArrivalTime":"2025-03-28T20:04:36Z","AimedDepartureTime":"2025-03-28T20:05:00Z","ExpectedDepartureTime":null,"Distances":""}}},{"RecordedAtTime":"2025-03-28T19:48:42Z","MonitoringRef":"17073","MonitoredVehicleJourney":{"LineRef":"J","DirectionRef":"IB","FramedVehicleJourneyRef":{"DataFrameRef":"2025-03-28","DatedVehicleJourneyRef":"11734693_M31"},"PublishedLineName":"CHURCH","OperatorRef":"SF","OriginRef":"17778","OriginName":"San Jose Ave & Geneva Ave","DestinationRef":"16992","DestinationName":"Metro Embarcadero Station","Monitored":true,"InCongestion":null,"VehicleLocation":{"Longitude":"-122.447281","Latitude":"37.7218208"},"Bearing":"0.0000000000","Occupancy":"seatsAvailable","VehicleRef":"2027","MonitoredCall":{"StopPointRef":"17073","StopPointName":"Church St & Market St","VehicleLocationAtStop":"","VehicleAtStop":"false","DestinationDisplay":"Embarcadero Station","AimedArrivalTime":"2025-03-28T20:17:37Z","ExpectedArrivalTime":"2025-03-28T20:18:06Z","AimedDepartureTime":"2025-03-28T20:17:37Z","ExpectedDepartureTime":null,"Distances":""}}},{"RecordedAtTime":"1970-01-01T00:00:00Z","MonitoringRef":"17073","MonitoredVehicleJourney":{"LineRef":"J","DirectionRef":"IB","FramedVehicleJourneyRef":{"DataFrameRef":"2025-03-28","DatedVehicleJourneyRef":"11734714_M31"},"PublishedLineName":"CHURCH","OperatorRef":"SF","OriginRef":"17778","OriginName":"San Jose Ave & Geneva Ave","DestinationRef":"16992","DestinationName":"Metro Embarcadero Station","Monitored":true,"InCongestion":null,"VehicleLocation":{"Longitude":"","Latitude":""},"Bearing":null,"Occupancy":null,"VehicleRef":null,"MonitoredCall":{"StopPointRef":"17073","StopPointName":"Church St & Market St","VehicleLocationAtStop":"","VehicleAtStop":"","DestinationDisplay":"Embarcadero Station","AimedArrivalTime":"2025-03-28T20:32:44Z","ExpectedArrivalTime":"2025-03-28T20:34:06Z","AimedDepartureTime":"2025-03-28T20:32:44Z","ExpectedDepartureTime":null,"Distances":""}}}]}}}