{"ServiceDelivery":{"ResponseTimestamp":"2025-04-01T14:23:14Z","ProducerRef":"SF","Status":true,"StopMonitoringDelivery":{"version":"1.4","ResponseTimestamp":"2025-04-01T14:23:14Z","Status":true,"MonitoredStopVisit":[{"RecordedAtTime":"2025-04-01T14:23:11Z","MonitoringRef":"17073","MonitoredVehicleJourney":{"LineRef":"22","DirectionRef":"IB","FramedVehicleJourneyRef":{"DataFrameRef":"2025-04-01","DatedVehicleJourneyRef":"11749332_M31"},"PublishedLineName":"FILLMORE","OperatorRef":"SF","OriginRef":"17765","OriginName":"Mission Bay North & 3rd St","DestinationRef":"14603","DestinationName":"Fillmore St & Bay St","Monitored":true,"InCongestion":null,"VehicleLocation":{"Longitude":"-122.42878","Latitude":"37.7652435"},"Bearing":"345.0000000000","Occupancy":"standingAvailable","VehicleRef":"5742","MonitoredCall":{"StopPointRef":"17073","StopPointName":"Church St & Market St","VehicleLocationAtStop":"","VehicleAtStop":"false","DestinationDisplay":"Bay Street","AimedArrivalTime":"2025-04-01T14:26:00Z","ExpectedArrivalTime":"2025-04-01T14:24:25Z","AimedDepartureTime":"2025-04-01T14:26:00Z","ExpectedDepartureTime":null,"Distances":""}}},{"RecordedAtTime":"2025-04-01T14:23:11Z","MonitoringRef":"17073","MonitoredVehicleJourney":{"LineRef":"22","DirectionRef":"IB","FramedVehicleJourneyRef":{"DataFrameRef":"2025-04-01","DatedVehicleJourneyRef":"11749179_M31"},"PublishedLineName":"FILLMORE","OperatorRef":"SF","OriginRef":"13281","OriginName":"16th St & Bryant St","DestinationRef":"14603","DestinationName":"Fillmore St & Bay St","Monitored":true,"InCongestion":null,"VehicleLocation":{"Longitude":"-122.42173","Latitude":"37.7649956"},"Bearing":"270.0000000000","Occupancy":"seatsAvailable","VehicleRef":"5713","MonitoredCall":{"StopPointRef":"17073","StopPointName":"Church St & Market St","VehicleLocationAtStop":"","VehicleAtStop":"false","DestinationDisplay":"Bay Street","AimedArrivalTime":"2025-04-01T14:29:00Z","ExpectedArrivalTime":"2025-04-01T14:27:25Z","AimedDepartureTime":"2025-04-01T14:29:00Z","ExpectedDepartureTime":null,"Distances":""}}},{"RecordedAtTime":"2025-04-01T14:23:11Z","MonitoringRef":"17073","MonitoredVehicleJourney":{"LineRef":"J","DirectionRef":"IB","FramedVehicleJourneyRef":{"DataFrameRef":"2025-04-01","DatedVehicleJourneyRef":"11734680_M31"},"PublishedLineName":"CHURCH","OperatorRef":"SF","OriginRef":"17778","OriginName":"San Jose Ave & Geneva Ave","DestinationRef":"16992","DestinationName":"Metro Embarcadero Station","Monitored":true,"InCongestion":null,"VehicleLocation":{"Longitude":"-122.427689","Latitude":"37.7543335"},"Bearing":"345.0000000000","Occupancy":"seatsAvailable","VehicleRef":"2064","MonitoredCall":{"StopPointRef":"17073","StopPointName":"Church St & Market St","VehicleLocationAtStop":"","VehicleAtStop":"false","DestinationDisplay":"Embarcadero Station","AimedArrivalTime":"2025-04-01T14:32:37Z","ExpectedArrivalTime":"2025-04-01T14:31:19Z","AimedDepartureTime":"2025-04-01T14:32:37Z","ExpectedDepartureTime":null,"Distances":""}}},{"RecordedAtTime":"2025-04-01T14:23:11Z","MonitoringRef":"17073","MonitoredVehicleJourney":{"LineRef":"22","DirectionRef":"IB","FramedVehicleJourneyRef":{"DataFrameRef":"2025-04-01","DatedVehicleJourneyRef":"11749333_M31"},"PublishedLineName":"FILLMORE","OperatorRef":"SF","OriginRef":"17765","OriginName":"Mission Bay North & 3rd St","DestinationRef":"14603","DestinationName":"Fillmore St & Bay St","Monitored":true,"InCongestion":null,"VehicleLocation":{"Longitude":"-122.399605","Latitude":"37.7663231"},"Bearing":"255.0000000000","Occupancy":"seatsAvailable","VehicleRef":"5707","MonitoredCall":{"StopPointRef":"17073","StopPointName":"Church St & Market St","VehicleLocationAtStop":"","VehicleAtStop":"false","DestinationDisplay":"Bay Street","AimedArrivalTime":"2025-04-01T14:37:00Z","ExpectedArrivalTime":"2025-04-01T14:37:31Z","AimedDepartureTime":"2025-04-01T14:37:00Z","ExpectedDepartureTime":null,"Distances":""}}},{"RecordedAtTime":"2025-04-01T14:23:11Z","MonitoringRef":"17073","MonitoredVehicleJourney":{"LineRef":"J","DirectionRef":"IB","FramedVehicleJourneyRef":{"DataFrameRef":"2025-04-01","DatedVehicleJourneyRef":"11734699_M31"},"PublishedLineName":"CHURCH","OperatorRef":"SF","OriginRef":"17778","OriginName":"San Jose Ave & Geneva Ave","DestinationRef":"16992","DestinationName":"Metro Embarcadero Station","Monitored":true,"InCongestion":null,"VehicleLocation":{"Longitude":"-122.44397","Latitude":"37.7238998"},"Bearing":"30.0000000000","Occupancy":"seatsAvailable","VehicleRef":"2002","MonitoredCall":{"StopPointRef":"17073","StopPointName":"Church St & Market St","VehicleLocationAtStop":"","VehicleAtStop":"false","DestinationDisplay":"Embarcadero Station","AimedArrivalTime":"2025-04-01T14:47:37Z","ExpectedArrivalTime":"2025-04-01T14:48:37Z","AimedDepartureTime":"2025-04-01T14:47:37Z","ExpectedDepartureTime":null,"Distances":""}}},{"RecordedAtTime":"2025-04-01T14:23:11Z","MonitoringRef":"17073","MonitoredVehicleJourney":{"LineRef":"J","DirectionRef":"IB","FramedVehicleJourneyRef":{"DataFrameRef":"2025-04-01","DatedVehicleJourneyRef":"11734733_M31"},"PublishedLineName":"CHURCH","OperatorRef":"SF","OriginRef":"17778","OriginName":"San Jose Ave & Geneva Ave","DestinationRef":"16992","DestinationName":"Metro Embarcadero Station","Monitored":true,"InCongestion":null,"VehicleLocation":{"Longitude":"-122.447067","Latitude":"37.7210655"},"Bearing":"120.0000000000","Occupancy":"seatsAvailable","VehicleRef":"2113","MonitoredCall":{"StopPointRef":"17073","StopPointName":"Church St & Market St","VehicleLocationAtStop":"","VehicleAtStop":"false","DestinationDisplay":"Embarcadero Station","AimedArrivalTime":"2025-04-01T15:02:30Z","ExpectedArrivalTime":"2025-04-01T15:01:54Z","AimedDepartureTime":"2025-04-01T15:02:30Z","ExpectedDepartureTime":null,"Distances":""}}}]}}}