{"ServiceDelivery":{"ResponseTimestamp":"2025-04-01T17:41:26Z","ProducerRef":"SF","Status":true,"StopMonitoringDelivery":{"version":"1.4","ResponseTimestamp":"2025-04-01T17:41:26Z","Status":true,"MonitoredStopVisit":[{"RecordedAtTime":"2025-04-01T17:41:16Z","MonitoringRef":"17073","MonitoredVehicleJourney":{"LineRef":"22","DirectionRef":"IB","FramedVehicleJourneyRef":{"DataFrameRef":"2025-04-01","DatedVehicleJourneyRef":"11749259_M31"},"PublishedLineName":"FILLMORE","OperatorRef":"SF","OriginRef":"17765","OriginName":"Mission Bay North & 3rd St","DestinationRef":"14603","DestinationName":"Fillmore St & Bay St","Monitored":true,"InCongestion":null,"VehicleLocation":{"Longitude":"-122.415352","Latitude":"37.7653656"},"Bearing":"255.0000000000","Occupancy":"standingAvailable","VehicleRef":"5708","MonitoredCall":{"StopPointRef":"17073","StopPointName":"Church St & Market St","VehicleLocationAtStop":"","VehicleAtStop":"false","DestinationDisplay":"Bay Street","AimedArrivalTime":"2025-04-01T17:43:00Z","ExpectedArrivalTime":"2025-04-01T17:49:07Z","AimedDepartureTime":"2025-04-01T17:43:00Z","ExpectedDepartureTime":null,"Distances":""}}},{"RecordedAtTime":"2025-04-01T17:41:16Z","MonitoringRef":"17073","MonitoredVehicleJourney":{"LineRef":"22","DirectionRef":"IB","FramedVehicleJourneyRef":{"DataFrameRef":"2025-04-01","DatedVehicleJourneyRef":"11749260_M31"},"PublishedLineName":"FILLMORE","OperatorRef":"SF","OriginRef":"17765","OriginName":"Mission Bay North & 3rd St","DestinationRef":"14603","DestinationName":"Fillmore St & Bay St","Monitored":true,"InCongestion":null,"VehicleLocation":{"Longitude":"-122.413956","Latitude":"37.7654343"},"Bearing":"255.0000000000","Occupancy":"seatsAvailable","VehicleRef":"5723","MonitoredCall":{"StopPointRef":"17073","StopPointName":"Church St & Market St","VehicleLocationAtStop":"","VehicleAtStop":"false","DestinationDisplay":"Bay Street","AimedArrivalTime":"2025-04-01T17:49:00Z","ExpectedArrivalTime":"2025-04-01T17:49:56Z","AimedDepartureTime":"2025-04-01T17:49:00Z","ExpectedDepartureTime":null,"Distances":""}}},{"RecordedAtTime":"2025-04-01T17:41:16Z","MonitoringRef":"17073","MonitoredVehicleJourney":{"LineRef":"J","DirectionRef":"IB","FramedVehicleJourneyRef":{"DataFrameRef":"2025-04-01","DatedVehicleJourneyRef":"11734722_M31"},"PublishedLineName":"CHURCH","OperatorRef":"SF","OriginRef":"17778","OriginName":"San Jose Ave & Geneva Ave","DestinationRef":"16992","DestinationName":"Metro Embarcadero Station","Monitored":true,"InCongestion":null,"VehicleLocation":{"Longitude":"-122.427414","Latitude":"37.7515182"},"Bearing":"345.0000000000","Occupancy":"seatsAvailable","VehicleRef":"2049","MonitoredCall":{"StopPointRef":"17073","StopPointName":"Church St & Market St","VehicleLocationAtStop":"","VehicleAtStop":"false","DestinationDisplay":"Embarcadero Station","AimedArrivalTime":"2025-04-01T17:47:37Z","ExpectedArrivalTime":"2025-04-01T17:51:46Z","AimedDepartureTime":"2025-04-01T17:47:37Z","ExpectedDepartureTime":null,"Distances":""}}},{"RecordedAtTime":"2025-04-01T17:41:16Z","MonitoringRef":"17073","MonitoredVehicleJourney":{"LineRef":"22","DirectionRef":"IB","FramedVehicleJourneyRef":{"DataFrameRef":"2025-04-01","DatedVehicleJourneyRef":"11749261_M31"},"PublishedLineName":"FILLMORE","OperatorRef":"SF","OriginRef":"17765","OriginName":"Mission Bay North & 3rd St","DestinationRef":"14603","DestinationName":"Fillmore St & Bay St","Monitored":true,"InCongestion":null,"VehicleLocation":{"Longitude":"-122.405182","Latitude":"37.7659874"},"Bearing":"255.0000000000","Occupancy":"seatsAvailable","VehicleRef":"5711","MonitoredCall":{"StopPointRef":"17073","StopPointName":"Church St & Market St","VehicleLocationAtStop":"","VehicleAtStop":"false","DestinationDisplay":"Bay Street","AimedArrivalTime":"2025-04-01T17:56:00Z","ExpectedArrivalTime":"2025-04-01T17:53:44Z","AimedDepartureTime":"2025-04-01T17:56:00Z","ExpectedDepartureTime":null,"Distances":""}}},{"RecordedAtTime":"2025-04-01T17:41:16Z","MonitoringRef":"17073","MonitoredVehicleJourney":{"LineRef":"J","DirectionRef":"IB","FramedVehicleJourneyRef":{"DataFrameRef":"2025-04-01","DatedVehicleJourneyRef":"11734721_M31"},"PublishedLineName":"CHURCH","OperatorRef":"SF","OriginRef":"17778","OriginName":"San Jose Ave & Geneva Ave","DestinationRef":"16992","DestinationName":"Metro Embarcadero Station","Monitored":true,"InCongestion":null,"VehicleLocation":{"Longitude":"-122.442513","Latitude":"37.725666"},"Bearing":"30.0000000000","Occupancy":"seatsAvailable","VehicleRef":"2064","MonitoredCall":{"StopPointRef":"17073","StopPointName":"Church St & Market St","VehicleLocationAtStop":"","VehicleAtStop":"false","DestinationDisplay":"Embarcadero Station","AimedArrivalTime":"2025-04-01T18:02:37Z","ExpectedArrivalTime":"2025-04-01T18:04:54Z","AimedDepartureTime":"2025-04-01T18:02:37Z","ExpectedDepartureTime":null,"Distances":""}}},{"RecordedAtTime":"1970-01-01T00:00:00Z","MonitoringRef":"17073","MonitoredVehicleJourney":{"LineRef":"J","DirectionRef":"IB","FramedVehicleJourneyRef":{"DataFrameRef":"2025-04-01","DatedVehicleJourneyRef":"11734695_M31"},"PublishedLineName":"CHURCH","OperatorRef":"SF","OriginRef":"17778","OriginName":"San Jose Ave & Geneva Ave","DestinationRef":"16992","DestinationName":"Metro Embarcadero Station","Monitored":true,"InCongestion":null,"VehicleLocation":{"Longitude":"","Latitude":""},"Bearing":null,"Occupancy":null,"VehicleRef":null,"MonitoredCall":{"StopPointRef":"17073","StopPointName":"Church St & Market St","VehicleLocationAtStop":"","VehicleAtStop":"","DestinationDisplay":"Embarcadero Station","AimedArrivalTime":"2025-04-01T18:17:37Z","ExpectedArrivalTime":"2025-04-01T18:18:20Z","AimedDepartureTime":"2025-04-01T18:17:37Z","ExpectedDepartureTime":null,"Distances":""}}}]}}}