{"ServiceDelivery":{"ResponseTimestamp":"2025-03-27T14:33:20Z","ProducerRef":"SF","Status":true,"StopMonitoringDelivery":{"version":"1.4","ResponseTimestamp":"2025-03-27T14:33:20Z","Status":true,"MonitoredStopVisit":[{"RecordedAtTime":"2025-03-27T14:33:14Z","MonitoringRef":"14448","MonitoredVehicleJourney":{"LineRef":"N","DirectionRef":"IB","FramedVehicleJourneyRef":{"DataFrameRef":"2025-03-27","DatedVehicleJourneyRef":"11738435_M21"},"PublishedLineName":"JUDAH","OperatorRef":"SF","OriginRef":"15223","OriginName":"Judah/La Playa/Ocean Beach","DestinationRef":"15239","DestinationName":"King St & 4th St","Monitored":true,"InCongestion":null,"VehicleLocation":{"Longitude":"-122.448883","Latitude":"37.7663574"},"Bearing":"60.0000000000","Occupancy":"seatsAvailable","VehicleRef":"2064","MonitoredCall":{"StopPointRef":"14448","StopPointName":"Duboce Ave & Church St","VehicleLocationAtStop":"","VehicleAtStop":"false","DestinationDisplay":"Caltrain/Ballpark","AimedArrivalTime":"2025-03-27T14:35:00Z","ExpectedArrivalTime":"2025-03-27T14:37:49Z","AimedDepartureTime":"2025-03-27T14:35:00Z","ExpectedDepartureTime":null,"Distances":""}}},{"RecordedAtTime":"2025-03-27T14:33:14Z","MonitoringRef":"14448","MonitoredVehicleJourney":{"LineRef":"N","DirectionRef":"IB","FramedVehicleJourneyRef":{"DataFrameRef":"2025-03-27","DatedVehicleJourneyRef":"11738436_M21"},"PublishedLineName":"JUDAH","OperatorRef":"SF","OriginRef":"15223","OriginName":"Judah/La Playa/Ocean Beach","DestinationRef":"15239","DestinationName":"King St & 4th St","Monitored":true,"InCongestion":null,"VehicleLocation":{"Longitude":"-122.466232","Latitude":"37.7627068"},"Bearing":"0.0000000000","Occupancy":"seatsAvailable","VehicleRef":"2034","MonitoredCall":{"StopPointRef":"14448","StopPointName":"Duboce Ave & Church St","VehicleLocationAtStop":"","VehicleAtStop":"false","DestinationDisplay":"Caltrain/Ballpark","AimedArrivalTime":"2025-03-27T14:45:00Z","ExpectedArrivalTime":"2025-03-27T14:46:48Z","AimedDepartureTime":"2025-03-27T14:45:00Z","ExpectedDepartureTime":null,"Distances":""}}},{"RecordedAtTime":"2025-03-27T14:33:14Z","MonitoringRef":"14448","MonitoredVehicleJourney":{"LineRef":"N","DirectionRef":"IB","FramedVehicleJourneyRef":{"DataFrameRef":"2025-03-27","DatedVehicleJourneyRef":"11738468_M21"},"PublishedLineName":"JUDAH","OperatorRef":"SF","OriginRef":"15223","OriginName":"Judah/La Playa/Ocean Beach","DestinationRef":"15239","DestinationName":"King St & 4th St","Monitored":true,"InCongestion":null,"VehicleLocation":{"Longitude":"-122.481491","Latitude":"37.7615013"},"Bearing":"75.0000000000","Occupancy":"seatsAvailable","VehicleRef":"2010","MonitoredCall":{"StopPointRef":"14448","StopPointName":"Duboce Ave & Church St","VehicleLocationAtStop":"","VehicleAtStop":"false","DestinationDisplay":"Caltrain/Ballpark","AimedArrivalTime":"2025-03-27T14:55:00Z","ExpectedArrivalTime":"2025-03-27T14:54:54Z","AimedDepartureTime":"2025-03-27T14:55:00Z","ExpectedDepartureTime":null,"Distances":""}}}]}}}